metacatalog_api/__init__.py
metacatalog_api/__version__.py
metacatalog_api/access_control.py
metacatalog_api/cli.py
metacatalog_api/core.py
metacatalog_api/db.py
metacatalog_api/default_server.py
metacatalog_api/file_uploads.py
metacatalog_api/migrate.py
metacatalog_api/models.py
metacatalog_api/server.py
metacatalog_api/utils.py
metacatalog_api/apps/__init__.py
metacatalog_api/apps/explorer/__init__.py
metacatalog_api/apps/explorer/create.py
metacatalog_api/apps/explorer/read.py
metacatalog_api/apps/explorer/upload.py
metacatalog_api/extra/__init__.py
metacatalog_api/extra/geocoder.py
metacatalog_api/router/__init__.py
metacatalog_api/router/api/__init__.py
metacatalog_api/router/api/create.py
metacatalog_api/router/api/data.py
metacatalog_api/router/api/export.py
metacatalog_api/router/api/preview.py
metacatalog_api/router/api/read.py
metacatalog_api/router/api/security.py
metacatalog_api/router/api/share.py
metacatalog_api/router/api/share_provider.py
metacatalog_api/router/api/upload.py
metacatalog_api/sql/authors_by_name.sql
metacatalog_api/sql/entries_locations.sql
metacatalog_api/sql/ftl_search_entries.sql
metacatalog_api/sql/search_entries.sql
metacatalog_api/sql/maintain/defaults.sql
metacatalog_api/sql/maintain/install.sql
metacatalog_api/sql/migrate/migration_1.sql
metacatalog_api/sql/migrate/migration_2.sql
metacatalog_api/sql/migrate/migration_3.sql
metacatalog_api/sql/migrate/migration_4.sql
metacatalog_api/sql/migrate/migration_5.sql
metacatalog_api-0.5.0.dist-info/licenses/LICENSE
metacatalog_api-0.5.0.dist-info/METADATA
metacatalog_api-0.5.0.dist-info/WHEEL
metacatalog_api-0.5.0.dist-info/top_level.txt
metacatalog_api-0.5.0.dist-info/RECORD
