Metadata-Version: 2.4
Name: metacatalog-api
Version: 0.5.0
Summary: FastAPI backend for managing a Metacatalog instance
Home-page: https://github.com/vforwater/metacatalog-api
Author: Mirko Mälicke
Author-email: mirko.maelicke@kit.edu
License: MIT
Classifier: Programming Language :: Python :: 3
Classifier: License :: OSI Approved :: MIT License
Classifier: Operating System :: OS Independent
Requires-Python: >=3.9
License-File: LICENSE
Requires-Dist: fastapi
Requires-Dist: pydantic
Requires-Dist: Jinja2
Requires-Dist: python-dotenv
Requires-Dist: uvicorn
Requires-Dist: pydantic-geojson
Requires-Dist: pydantic-settings
Requires-Dist: python-multipart
Requires-Dist: dateparser
Requires-Dist: sqlmodel
Requires-Dist: geoalchemy2
Requires-Dist: psycopg2-binary
Requires-Dist: shapely
Requires-Dist: ipython
Requires-Dist: polars
Requires-Dist: httpx
Dynamic: author
Dynamic: author-email
Dynamic: classifier
Dynamic: description
Dynamic: description-content-type
Dynamic: home-page
Dynamic: license
Dynamic: license-file
Dynamic: requires-dist
Dynamic: requires-python
Dynamic: summary
